{
  "creds": {
    "noiseKey": {
      "private": {
        "type": "Buffer",
        "data": "oDBOl8hnmdPzKT0VzDxh9lg7OrDCFkPoS104a3oQ2EU="
      },
      "public": {
        "type": "Buffer",
        "data": "H404tp5Z7/nhEYb3b3KuSag2VrXe2IrmdvgkTfCUZjo="
      }
    },
    "signedIdentityKey": {
      "private": {
        "type": "Buffer",
        "data": "ICw1wzmI64X/xjHkbfMmePeq/7vWKnt61NEq8R3PLUo="
      },
      "public": {
        "type": "Buffer",
        "data": "1BHVRLZyaCCPMGd52U9l4ONJRwegMeJWoXvLb9t9v1I="
      }
    },
    "signedPreKey": {
      "keyPair": {
        "private": {
          "type": "Buffer",
          "data": "6NwG9oZ9yQDyHmCzOPAb/minTwRc8tAAqZRSbkPP/XU="
        },
        "public": {
          "type": "Buffer",
          "data": "+BaYLzzUK7UBAJbezzyDiTUpY/910rUadftmmsPLOkw="
        }
      },
      "signature": {
        "type": "Buffer",
        "data": "VvkItVCfEcZp7i3YYHQy2/vsSpeoFE2fnZcaxDHCQDy4WA3uJUZF0rG4ZmGRu1/hMmp6Fw0RR+TQkgVi9atoCA=="
      },
      "keyId": 1
    },
    "registrationId": 145,
    "advSecretKey": "VK4AQlyG29Y+B/mGEgkGrg94Pn0Tii2AmIFPdQ8CF34=",
    "processedHistoryMessages": [
      {
        "key": {
          "remoteJid": "62881036181320@s.whatsapp.net",
          "fromMe": true,
          "id": "F638E8EF74C8CE6BDAD1CA7B5C9168B1"
        },
        "messageTimestamp": 1678110315
      },
      {
        "key": {
          "remoteJid": "62881036181320@s.whatsapp.net",
          "fromMe": true,
          "id": "A887BCD0FA7D83A7F3E1F6E4089FB2B7"
        },
        "messageTimestamp": 1678110316
      },
      {
        "key": {
          "remoteJid": "62881036181320@s.whatsapp.net",
          "fromMe": true,
          "id": "9674760C16BD3C940BC01D92B1C98FFE"
        },
        "messageTimestamp": 1678110324
      }
    ],
    "nextPreKeyId": 31,
    "firstUnuploadedPreKeyId": 31,
    "accountSettings": {
      "unarchiveChats": false
    },
    "account": {
      "details": "CI3nyocHEOTcl6AGGAU=",
      "accountSignatureKey": "5ssulZ0B5RJBVB6BjdYKTpEcVlOh4iN4P7u1Vpst5yI=",
      "accountSignature": "eEiMmB2UZ8wejxiSiw4bst4Q25bMjmDG1qx52N3oaP7cJpRpHS4Fpd8e6gyhcmVFYSbj5RP1MBo6EC8DEvlxBA==",
      "deviceSignature": "5obmwPLTPf3WFWqry2UDJ5Ge0wtf6D5asSfPdXRgX3NxAj8/hCzBQcGbupa58f2Y6t6QXwvTXRJp5D9iY3L+CA=="
    },
    "me": {
      "id": "62881036181320:98@s.whatsapp.net",
      "name": "Matchaadepanmu"
    },
    "signalIdentities": [
      {
        "identifier": {
          "name": "62881036181320:98@s.whatsapp.net",
          "deviceId": 0
        },
        "identifierKey": {
          "type": "Buffer",
          "data": "BebLLpWdAeUSQVQegY3WCk6RHFZToeIjeD+7tVabLeci"
        }
      }
    ],
    "platform": "android",
    "lastAccountSyncTimestamp": 1678110379,
    "myAppStateKeyId": "AAAAAPXl"
  },
  "keys": {
    "preKeys": {
      "1": {
        "private": {
          "type": "Buffer",
          "data": "CLS8d6kcxsPEy80ZOY2iz8Wgae/u6DtsPdtr/NUcVXg="
        },
        "public": {
          "type": "Buffer",
          "data": "HJUTJGFEQb5ccsefOl3OlbrJyaP/vN/jJtk4RGOyK1g="
        }
      },
      "2": {
        "private": {
          "type": "Buffer",
          "data": "qKYK0DvcWoXVtyAnvdQILvdxhkyF4WAsAJZuz+jxg3M="
        },
        "public": {
          "type": "Buffer",
          "data": "4aHI6Lmt9hiqUthb9nsrTZjHlcJUmdMXM3561ZvbgjQ="
        }
      },
      "3": {
        "private": {
          "type": "Buffer",
          "data": "AG39XnbYzJ2K+ZhWlLutQ7zCH4Rb4YuFCdKUv4sc4Ho="
        },
        "public": {
          "type": "Buffer",
          "data": "CLiREUneoymnCf0WEGtLmQQWKKwwVVNu0A3HvnIL4l8="
        }
      },
      "4": {
        "private": {
          "type": "Buffer",
          "data": "kLl/qYqLgMRLCr85NRh8ikm1nMeweao1Hdv57dzMAFU="
        },
        "public": {
          "type": "Buffer",
          "data": "EovjAvjd5Mozq0bbWeLTo7v7NiSzf2Oh5S2yg8jMy1Q="
        }
      },
      "5": {
        "private": {
          "type": "Buffer",
          "data": "QD8orf41+dhFj3QHZ6E8UoiSfjoCZDP5vkrqNkGaMnI="
        },
        "public": {
          "type": "Buffer",
          "data": "oKdtCj7K1SgGc7DjuTS8WyOQaM4MjKgKlqpxGQokMAw="
        }
      },
      "6": {
        "private": {
          "type": "Buffer",
          "data": "8PNbDv3UxMQMEKbCJiWpSwAp4ofK6ns8GEK6Ucg/v0g="
        },
        "public": {
          "type": "Buffer",
          "data": "tu6ktyWnBDFU9zNt5XCYvHtTJX0ry/ZF5tRNk6lIbyA="
        }
      },
      "7": {
        "private": {
          "type": "Buffer",
          "data": "OPLFdCv632rOvUCUUmLFCVa4kPawJdkaM2rfYN+nk1U="
        },
        "public": {
          "type": "Buffer",
          "data": "+CDQumeySnoR2In6zwok1VrxXfwGFKMNcQFA9gZUgEw="
        }
      },
      "8": {
        "private": {
          "type": "Buffer",
          "data": "wABc+Eu317ePOH7myA5PkmuwmE9GbwQBXcIe3cVuEGo="
        },
        "public": {
          "type": "Buffer",
          "data": "w38AClnur8xAf9hd5dI1LXuxP5hISBLpK/PW4ZF8lVQ="
        }
      },
      "9": {
        "private": {
          "type": "Buffer",
          "data": "oNH0u5sMLy1IgtcQMgKXQ196srO7TPmKL+jJOpIH4HU="
        },
        "public": {
          "type": "Buffer",
          "data": "b/krUspp8+LkK+hYdM5zBJSbO7xVRluvZuWbFojh528="
        }
      },
      "10": null,
      "11": {
        "private": {
          "type": "Buffer",
          "data": "IAFrSpUihwPMkU8WeRRoCAmI4YkTSHLurm8OoaFH6FE="
        },
        "public": {
          "type": "Buffer",
          "data": "P265SFJzdDfTv2IwFpjXEnSd863dQOOaq5hlM+6wyFg="
        }
      },
      "12": {
        "private": {
          "type": "Buffer",
          "data": "yENVlIj+eXg6nSvqWARIJPfsn1NGdXrL9uSTU+OrD2g="
        },
        "public": {
          "type": "Buffer",
          "data": "WASP9NpoKfq72uPblB5bZw1vAiWpAWs0EfDusFszWxE="
        }
      },
      "13": {
        "private": {
          "type": "Buffer",
          "data": "MPDp+jZRN1nez1h2XeTgjA+Y0lT6ufZDfrlGIW6FsHU="
        },
        "public": {
          "type": "Buffer",
          "data": "hocD8l5apfpxHuX3wOe32BivLja0fnGyRyARVvR5mls="
        }
      },
      "14": {
        "private": {
          "type": "Buffer",
          "data": "iA/HAx0Uiflm5GkEPusBrqdgQ0ByaeaTVWCAL0Vuz28="
        },
        "public": {
          "type": "Buffer",
          "data": "ql3yubJGFPSnE29SEWJWPcVbS3mDSt/30D8iXEi1AQc="
        }
      },
      "15": {
        "private": {
          "type": "Buffer",
          "data": "0A6mw2wOCDFZaajZshwJTmzSzXgxG18cscEpgOfJnHo="
        },
        "public": {
          "type": "Buffer",
          "data": "egzITUeb2m9SZtmVbiMwkSy7W1du+kyPuQrNo/x7LGQ="
        }
      },
      "16": {
        "private": {
          "type": "Buffer",
          "data": "iDogkTUmRK+RC5ZXafqH3CMvlDocOzQkFdavQZmF1HE="
        },
        "public": {
          "type": "Buffer",
          "data": "Sp3AFrVHqBa4LbpGo8fSb29pb318GXgxTbBb6L8Ni0E="
        }
      },
      "17": {
        "private": {
          "type": "Buffer",
          "data": "KAc9rsayMpKw2+lVGbm5IZXY6PDVx/mEVE//kVhQrUg="
        },
        "public": {
          "type": "Buffer",
          "data": "yPhpogcyABZWb6Rsxkt3RNHtpx67rirGPG2p2H6xtEI="
        }
      },
      "18": {
        "private": {
          "type": "Buffer",
          "data": "IFSnhNkIWvXaxh/f++C3oPLfe4LdewxK90lBnj4UyXE="
        },
        "public": {
          "type": "Buffer",
          "data": "VoQF6k4FZvUxMWqbRH3/njdAXi0mtTUeHrake5qu1j0="
        }
      },
      "19": {
        "private": {
          "type": "Buffer",
          "data": "8OIPn2nHMsjKAzOMukucQlz/GeKex5WBgUuoqEeIl24="
        },
        "public": {
          "type": "Buffer",
          "data": "agIf2tMEsGcxRmhZfZdvH7h3Uo8znJLch/hz5vfJFxQ="
        }
      },
      "20": {
        "private": {
          "type": "Buffer",
          "data": "yFjzzXxTjo+qjvvNjD1adEgQD/2BNKC/tObn3SCX3GM="
        },
        "public": {
          "type": "Buffer",
          "data": "UzZJQV93zZB8EFJvDJ5NMA7V+89V82rRIERMhl1StRw="
        }
      },
      "21": {
        "private": {
          "type": "Buffer",
          "data": "WM3eSLUIc9Ir/z6d+gA5KpS19xiOzI1T2Y+qWe+L/W4="
        },
        "public": {
          "type": "Buffer",
          "data": "evYaRqE3pX1EvfmBLzSl3Mv2MqglBPKjg0uqxccN8gk="
        }
      },
      "22": {
        "private": {
          "type": "Buffer",
          "data": "SJCOiJ0duRCLXQImvur4fwlkOUAN6g60NUEjbnD/Kmc="
        },
        "public": {
          "type": "Buffer",
          "data": "v+4PdqrbPq3ZPC9gQI+PnpVRJ3XGoWswBw1V+C/J+yQ="
        }
      },
      "23": null,
      "24": {
        "private": {
          "type": "Buffer",
          "data": "cC1hGKRPwoEf6b8Ae3hXHtpNj25Ou0raAdcEU+DGY24="
        },
        "public": {
          "type": "Buffer",
          "data": "CWmdqlREShNvdq2Tx93l5NIgTT+8gwcIzsvpuSgMCwg="
        }
      },
      "25": {
        "private": {
          "type": "Buffer",
          "data": "2D9H7N/BxURU/mx/f0R6UBPxC/UINe86dALVgAEnwUA="
        },
        "public": {
          "type": "Buffer",
          "data": "LmnB05VTrhfCBhhgfJtGA8B7EpJnLHkEAeVLS4eZDRM="
        }
      },
      "26": {
        "private": {
          "type": "Buffer",
          "data": "CEnyksV7Ov+WM8nkk7bo35cuG/sZeEecpf++k+bIa3U="
        },
        "public": {
          "type": "Buffer",
          "data": "8ihLRlt5rWxPruvlxVUEiXl9hY4tYV4hMAS6MlBgbjQ="
        }
      },
      "27": null,
      "28": {
        "private": {
          "type": "Buffer",
          "data": "6BFm+oOymKH6nn1psQZPn+u1XHh0/B89hFtZE/ZUMn0="
        },
        "public": {
          "type": "Buffer",
          "data": "yci/dhoriLDEVIIINUaJTMKTmg9G7gfXPK+N5LBbFnk="
        }
      },
      "29": {
        "private": {
          "type": "Buffer",
          "data": "SPCQ/4YSin8rxGUI0SUJoQTa9niIguZxPmmjkUagBlg="
        },
        "public": {
          "type": "Buffer",
          "data": "o7M+OPtAijxXylF6tlDn+WZWREoQa3RCJciRPnl6kHI="
        }
      },
      "30": null
    },
    "sessions": {
      "62881036181320.0": {
        "_sessions": {
          "BWobwJM1fkBs2mGGlir6/CUPmN8KgKlYlDwTBG9JLkww": {
            "registrationId": 1831285234,
            "currentRatchet": {
              "ephemeralKeyPair": {
                "pubKey": "BfY5HZb+jsM7oN5PgElSoL/tRaUq388yCrYMolTw85JH",
                "privKey": "UImY3RiGKl52TtC4yhF+lUfvJREr9RoiD0Wn18ZjhEA="
              },
              "lastRemoteEphemeralKey": "BTTOarnYW3sCTjwPyIM7V7hqFZCIdX/BvvJVxiPGP8tV",
              "previousCounter": 0,
              "rootKey": "xtev+g6PqIRRt4HfLeJkQNixquaYay86zZu9k6FVAdA="
            },
            "indexInfo": {
              "baseKey": "BWobwJM1fkBs2mGGlir6/CUPmN8KgKlYlDwTBG9JLkww",
              "baseKeyType": 2,
              "closed": -1,
              "used": 1678110313917,
              "created": 1678110313917,
              "remoteIdentityKey": "BebLLpWdAeUSQVQegY3WCk6RHFZToeIjeD+7tVabLeci"
            },
            "_chains": {
              "BTTOarnYW3sCTjwPyIM7V7hqFZCIdX/BvvJVxiPGP8tV": {
                "chainKey": {
                  "counter": 7,
                  "key": "X0IbZMfHwFNryueui+T2fuNUvPu9ZA2Wm1x3cttwZ10="
                },
                "chainType": 2,
                "messageKeys": {}
              },
              "BfY5HZb+jsM7oN5PgElSoL/tRaUq388yCrYMolTw85JH": {
                "chainKey": {
                  "counter": -1,
                  "key": "yrAdZ9DFnAQlC5W8J4p0OgP7ZG5V/FxQf6MzjIs1BeA="
                },
                "chainType": 1,
                "messageKeys": {}
              }
            }
          }
        },
        "version": "v1"
      },
      "6289519240209.0": {
        "_sessions": {
          "BTO8k2oGOUArPntdbReZlFyThpgo1Tx+SdfGmY2SAgsv": {
            "registrationId": 957490939,
            "currentRatchet": {
              "ephemeralKeyPair": {
                "pubKey": "BVk6RXI2NomJLA92CISxv/n5cgcrP8HLLlNaltBJX998",
                "privKey": "WHU0u9Z2i/FELg5RE2SkV33kLAuRl26RQWAc5tceGW0="
              },
              "lastRemoteEphemeralKey": "BUpOEzHJM7H/04YNnbjnJ9tBQBwrfygv1Ypud0OeyB0F",
              "previousCounter": 0,
              "rootKey": "2wlh4eDBj+Xqq6QfIMORkqqN0Pba1rYdl7aePzbY72c="
            },
            "indexInfo": {
              "baseKey": "BTO8k2oGOUArPntdbReZlFyThpgo1Tx+SdfGmY2SAgsv",
              "baseKeyType": 2,
              "closed": -1,
              "used": 1678110350970,
              "created": 1678110350950,
              "remoteIdentityKey": "BSlp4jsZMjDFRBfjnsvnIdN+BU8kzxZuxRz1689yUE8C"
            },
            "_chains": {
              "BUpOEzHJM7H/04YNnbjnJ9tBQBwrfygv1Ypud0OeyB0F": {
                "chainKey": {
                  "counter": 4,
                  "key": "55+Hv4SAJBNFnDadDtQf4YZw0+Vv+PR2vc6I1u2Sook="
                },
                "chainType": 2,
                "messageKeys": {}
              },
              "BVk6RXI2NomJLA92CISxv/n5cgcrP8HLLlNaltBJX998": {
                "chainKey": {
                  "counter": -1,
                  "key": "A+jBlZjDwtOOmatbHnnddLZ5/0tbvj4XkHytPmGWfho="
                },
                "chainType": 1,
                "messageKeys": {}
              }
            }
          }
        },
        "version": "v1"
      },
      "62881036181320:96.0": {
        "_sessions": {
          "BVClRzHEkCCsz8OgR89kYHBxaP/6f9IqcpDExGmcoJlv": {
            "registrationId": 165,
            "currentRatchet": {
              "ephemeralKeyPair": {
                "pubKey": "BcvzINti9PmkPVaASzkcUYRIzcQ3u9nPilkgjd1sfIhc",
                "privKey": "KK2YjnhyotqQXm9t6Qj3cm8iGGpVFqDrN4SALf3nJEY="
              },
              "lastRemoteEphemeralKey": "Bbd9qDxBbsYQP9682KOsUw99gbnEFysXg+ChAPPvo6RS",
              "previousCounter": 0,
              "rootKey": "kahnzZxPy14hV2pgxEpaEA+zhGjzeYPJ8yNsmihQum0="
            },
            "indexInfo": {
              "baseKey": "BVClRzHEkCCsz8OgR89kYHBxaP/6f9IqcpDExGmcoJlv",
              "baseKeyType": 2,
              "closed": 1678112539379,
              "used": 1678112539359,
              "created": 1678112539359,
              "remoteIdentityKey": "BaFSz5jGr/09/ZAQ/J1NDJrN9FOj4MvXDHwf7jmPESs6"
            },
            "_chains": {
              "Bbd9qDxBbsYQP9682KOsUw99gbnEFysXg+ChAPPvo6RS": {
                "chainKey": {
                  "counter": 0,
                  "key": "gMtVZoDuADwTHj45FuMhykIYfBpm1NNYCd40FnHQNhU="
                },
                "chainType": 2,
                "messageKeys": {}
              },
              "BcvzINti9PmkPVaASzkcUYRIzcQ3u9nPilkgjd1sfIhc": {
                "chainKey": {
                  "counter": -1,
                  "key": "tB1q3EzF9E8rZ8znZnW2PSHASUUP0+AwV10/jXyYd8w="
                },
                "chainType": 1,
                "messageKeys": {}
              }
            }
          },
          "BRbnYsGoloFKP3a+C5sLQ6D4z1fzWVOiP8tc9mflIV10": {
            "registrationId": 165,
            "currentRatchet": {
              "ephemeralKeyPair": {
                "pubKey": "BWKPRZ3gQspbh+HYTWiRNauFb5YGXkGWsSvvr+Y4/Vt6",
                "privKey": "8KP74CBfCpGWon8AywpA+mylgbqt6Ltw14XgM0kBhnY="
              },
              "lastRemoteEphemeralKey": "BQAC4B/KlAFSRpR5tH59jmnaEbM/4ag8t3S6GwNayhBV",
              "previousCounter": 0,
              "rootKey": "5iPJU2ACdSQwp27ApWel1yDm44xyemP5ZQM746Zk1HU="
            },
            "indexInfo": {
              "baseKey": "BRbnYsGoloFKP3a+C5sLQ6D4z1fzWVOiP8tc9mflIV10",
              "baseKeyType": 2,
              "closed": -1,
              "used": 1678112539388,
              "created": 1678112539388,
              "remoteIdentityKey": "BaFSz5jGr/09/ZAQ/J1NDJrN9FOj4MvXDHwf7jmPESs6"
            },
            "_chains": {
              "BQAC4B/KlAFSRpR5tH59jmnaEbM/4ag8t3S6GwNayhBV": {
                "chainKey": {
                  "counter": 2,
                  "key": "4TEDDRenoy9Wyan66kDEuFUNuzhvO/4zCGF+Zs+Hux4="
                },
                "chainType": 2,
                "messageKeys": {}
              },
              "BWKPRZ3gQspbh+HYTWiRNauFb5YGXkGWsSvvr+Y4/Vt6": {
                "chainKey": {
                  "counter": -1,
                  "key": "n0KHYke5epem22kbS3HVdKNaNT7KwVpYLxVGqN058nI="
                },
                "chainType": 1,
                "messageKeys": {}
              }
            }
          }
        },
        "version": "v1"
      }
    },
    "appStateSyncKeys": {
      "AAAAAPXm": {
        "keyData": "2GF/x2esnDkSrRcgYWk0Mq4c9Nh3+rDdvdSPj4Ynt2s=",
        "fingerprint": {
          "rawId": 1894953868,
          "currentIndex": 1,
          "deviceIndexes": [
            0,
            1
          ]
        },
        "timestamp": "1678082238683"
      },
      "AAAAAPXn": {
        "keyData": "D++KghHL6KUAqPaGWERhSBvzFnVEVtb+6KT8Rvjx5nM=",
        "fingerprint": {
          "rawId": 1894953869,
          "currentIndex": 1,
          "deviceIndexes": [
            0,
            1
          ]
        },
        "timestamp": "0"
      },
      "AAAAAPXl": {
        "keyData": "ljQDRxs5Tr3iE7pDENxKsSqX1uTId/SUn+7Qdxu96kU=",
        "fingerprint": {
          "rawId": 1894953867,
          "currentIndex": 1,
          "deviceIndexes": [
            0,
            1
          ]
        },
        "timestamp": "0"
      }
    },
    "appStateVersions": {
      "critical_block": {
        "version": 4,
        "hash": {
          "type": "Buffer",
          "data": "9DQlkFfLnr4xQ4zWwDJbsGx+tptm18cRyvwlENb44rfcnoFj5mU4ofKYdtmIgByUR0PjIu3ZVUk938FlaG3Pus1hQ9HgwEnTTo8Z4IGjuwqWj707OuzKBN0jz1vcb1shdlThQ/q2+NJFRWpE+p0kuLMvluF1xhtTyNceSErnLIM="
        },
        "indexValueMap": {
          "hAfdhzp2wSspCq9gfBVHWY5kRPrnCDKg4O7L2xl+gdI=": {
            "valueMac": {
              "type": "Buffer",
              "data": "qr4GCWAATCfXZZP3M8jTRHsO6yc4APNVwNWcgaCw2VE="
            }
          },
          "C5smpvyLyn7TmKe1YuDM7xmftZe/b5AnNbjndO5Yx5Q=": {
            "valueMac": {
              "type": "Buffer",
              "data": "EjT50hoELvaci1iYTNPQE4QwfC7QmpQhSAbEjCLvFG8="
            }
          },
          "+jcS0ePJhqHCuK0GMl2OyEaeOtYE7xm4ysWRZhQhBk0=": {
            "valueMac": {
              "type": "Buffer",
              "data": "tUIOmd7wC5iGN9Yi91rUINAwgUZ2MBZwVPnDWydZ8LI="
            }
          }
        }
      },
      "critical_unblock_low": null,
      "regular": {
        "version": 4,
        "hash": {
          "type": "Buffer",
          "data": "87AKRFIyLqmIf3wX3uEWuTz/eobsU5+KMQ/9CGQwnwKrtGrNXj6xm8SHFu72VtRKyrgRWSRipjQ2cRABe/JN50QjDuDl5E71ISucX7CSgePOyvrNVoxqWPwElMEPFQn5acv3LjDK+ZjnA2WUfxP319cMtc1egiVIArdjl0t8enk="
        },
        "indexValueMap": {
          "HpJKgE18XoD1Nlj1KBe+ZrGZTpZcLTbRYrcGt0MKQrE=": {
            "valueMac": {
              "type": "Buffer",
              "data": "P3K4gSiw129CLiLPRxe1JduRIAMywGRBANopPHqr744="
            }
          },
          "VUsbzgO64gXeppbc+rz0Dn/EZvMHKXw8ZfDOntdOpGs=": {
            "valueMac": {
              "type": "Buffer",
              "data": "KiKylnYluzs+Dx/YhTxKycHwVupZgWvDxylRkrwlWw4="
            }
          }
        }
      },
      "regular_high": {
        "version": 4,
        "hash": {
          "type": "Buffer",
          "data": "cb8aYMtTo4DGEpbkrxzjtnBZmETi2RMlPUSx/pii9tuYO5yeK6R0b7HLXHa1EEiEJT+1xGmc2P245DHBGKLS+hr9x7CKgHOAnDFlDkIf4tFsNPJ3f2iPR68TSJwRdJ2iQozX5YvUCtYpsHSvFlMWWaxKpq7Qbb7wqzZge249bnQ="
        },
        "indexValueMap": {
          "O0XzRgQNn2CuKGPm4oWoyCdasR4q3Vge4c5pf8aFBLM=": {
            "valueMac": {
              "type": "Buffer",
              "data": "YGFce3AoqpSkAo4Yi/mAWb61l/8lCIhGVn0vQ0ZVyK8="
            }
          },
          "+NNcUZRzQTl0ieRkEVkC/mZfsCyRLTjepE0eitChKXM=": {
            "valueMac": {
              "type": "Buffer",
              "data": "Heg7R7D7cDw7yaFepvqHNVV1PZ2a+ZT/41ozUhxcgwc="
            }
          }
        }
      },
      "regular_low": {
        "version": 8,
        "hash": {
          "type": "Buffer",
          "data": "Sf2pKCAzlJqB0LxZpjmiNp7OKb8rILFTyC8k00EdG9YqC6Z3x7z3FvLorBQDVB9JLpLoy0745kea66SYA1cWn24LIK94td2w7+ndth6h1SLa13Bo6R5ogoUCmG00NfbO+Vjz7ml9Hno3PKvCxe45F2yhi3W6Wx/eXS+OUik9v1A="
        },
        "indexValueMap": {
          "dv0BJGEcBb+1ZJo0g/OTU47yKj7f9aE9lcob/LRUdkk=": {
            "valueMac": {
              "type": "Buffer",
              "data": "mkV+SOORb569JjOBXQj2FB8sbW31fONWh1OPBbOH09E="
            }
          },
          "bjwtxHeC15WQvKzgp7JiIM7AlwzvYVwHzlC4cC83nL8=": {
            "valueMac": {
              "type": "Buffer",
              "data": "35wcpLO43PHauaaLlsPKSzGZkf/Z5Ox4t+bun82c0i8="
            }
          },
          "uWe+H3d0JSBmwTqH3I3zdefpoA7g0+WoMG+XwVb6/jw=": {
            "valueMac": {
              "type": "Buffer",
              "data": "jdl/b3HpRzGlInHWQAfRoao8HaCyFvkdVRevLCFi7F4="
            }
          },
          "8ZCFyD1TFVmJnWDb/uSDa8dPpMTSfq+Rms5vYHmx7jM=": {
            "valueMac": {
              "type": "Buffer",
              "data": "bFCxdcGi/axzbnNWi/Cw7qXW2gPld6QdKFYNEdzTWvQ="
            }
          },
          "dVBj02gTSSrhcd5NmfhxI2GfG8ufBRzYEZVFIh1Jy0s=": {
            "valueMac": {
              "type": "Buffer",
              "data": "0ul98rKHb+4ast0/Acz1td9h6ESpHj8dzaLCY+Vz3Ro="
            }
          },
          "B2GQxCHJwWZJD4AJ4ubEkYylvvR12hbVBWwoB8Ci4vw=": {
            "valueMac": {
              "type": "Buffer",
              "data": "PCtewu4FpEpkDWxnYUjKzqLIIQWLoaAURhfJECPgR0I="
            }
          },
          "lfvZM/DKf1Col2C8PBO5zUx7xpgiRh9HffXsoZl1Dzs=": {
            "valueMac": {
              "type": "Buffer",
              "data": "1z7aEUomsRiluJPVZI9zo2rN8QcFpLLFHnOhEmghRJA="
            }
          },
          "cpB0k1ZfOTI1KZkTkq47aCsQW2GAm8x6z+QRNASucHw=": {
            "valueMac": {
              "type": "Buffer",
              "data": "ofU1BnhPF+DLu+v0VeV9YjgrUkFG2mXPd+7t9V265Ns="
            }
          },
          "TKCq0kx01isaeZ3mO76yThE+7eogQ0NaVgC98iSqNSg=": {
            "valueMac": {
              "type": "Buffer",
              "data": "pENkQgUoXMOE8rCDbkOPowEBKXumwbILV2GFjQR7XF0="
            }
          }
        }
      }
    }
  }
}
